{
    "title": "Rewterz Threat Alert Shodi Malware Active IOCs",
    "url": "https://www.rewterz.com/rewterz-news/rewterz-threat-alert-shodi-malware-active-iocs-5",
    "threats": {
        "Threat": [
            {
                "token": {
                    "id": "<THREAT_0x5e7b1981>",
                    "type": "Threat",
                    "value": "shodi"
                },
                "references": {
                    "sentences": [],
                    "titles": [
                        "Rewterz Threat Alert Shodi Malware Active IOCs"
                    ]
                },
                "links": [
                    {
                        "src": {
                            "id": "<SHA256_0xf2a3ee3c>",
                            "type": "Hash",
                            "hash_type": "SHA256",
                            "value": "849b799a93fc53889229c731b298c9eea699f93790e0387589a155852fb53213"
                        },
                        "relation": "use_threat",
                        "dst": {
                            "id": "<THREAT_0x5e7b1981>",
                            "type": "Threat",
                            "value": "shodi"
                        }
                    },
                    {
                        "src": {
                            "id": "<FILE_0x898f782e>",
                            "type": "File",
                            "value": "usr_shohdi_photo_usr.jpg"
                        },
                        "relation": "use_threat",
                        "dst": {
                            "id": "<THREAT_0x5e7b1981>",
                            "type": "Threat",
                            "value": "shodi"
                        }
                    },
                    {
                        "src": {
                            "id": "<TTP_0x4f6a185>",
                            "type": "TTP",
                            "value": "ta0040"
                        },
                        "relation": "use_threat",
                        "dst": {
                            "id": "<THREAT_0x5e7b1981>",
                            "type": "Threat",
                            "value": "shodi"
                        }
                    },
                    {
                        "src": {
                            "id": "<SHA1_0x41f3cf0a>",
                            "type": "Hash",
                            "hash_type": "SHA1",
                            "value": "af8ddb111e5936a655c44b45b2ee171be4a56d93"
                        },
                        "relation": "use_threat",
                        "dst": {
                            "id": "<THREAT_0x5e7b1981>",
                            "type": "Threat",
                            "value": "shodi"
                        }
                    },
                    {
                        "src": {
                            "id": "<FILE_0xf4112668>",
                            "type": "File",
                            "value": "sol.exe"
                        },
                        "relation": "use_threat",
                        "dst": {
                            "id": "<THREAT_0x5e7b1981>",
                            "type": "Threat",
                            "value": "shodi"
                        }
                    },
                    {
                        "src": {
                            "id": "<MD5_0x3a90d8b4>",
                            "type": "Hash",
                            "hash_type": "MD5",
                            "value": "ae2901bab810c3d65352ec82b00e8605"
                        },
                        "relation": "use_threat",
                        "dst": {
                            "id": "<THREAT_0x5e7b1981>",
                            "type": "Threat",
                            "value": "shodi"
                        }
                    },
                    {
                        "src": {
                            "id": "<FILE_0x68bc808>",
                            "type": "File",
                            "value": "scandskw.exe"
                        },
                        "relation": "use_threat",
                        "dst": {
                            "id": "<THREAT_0x5e7b1981>",
                            "type": "Threat",
                            "value": "shodi"
                        }
                    },
                    {
                        "src": {
                            "id": "<CATEGORY_0x151cee5c>",
                            "type": "Category",
                            "value": "trojan"
                        },
                        "relation": "has_category",
                        "dst": {
                            "id": "<THREAT_0x5e7b1981>",
                            "type": "Threat",
                            "value": "shodi"
                        }
                    },
                    {
                        "src": {
                            "id": "<CATEGORY_0xf1a480bb>",
                            "type": "Category",
                            "value": "malware"
                        },
                        "relation": "has_category",
                        "dst": {
                            "id": "<THREAT_0x5e7b1981>",
                            "type": "Threat",
                            "value": "shodi"
                        }
                    },
                    {
                        "src": {
                            "id": "<FILE_0xa612fb14>",
                            "type": "File",
                            "value": "pbrush.exe"
                        },
                        "relation": "use_threat",
                        "dst": {
                            "id": "<THREAT_0x5e7b1981>",
                            "type": "Threat",
                            "value": "shodi"
                        }
                    },
                    {
                        "src": {
                            "id": "<TTP_0x4f6a185>",
                            "type": "TTP",
                            "value": "ta0040"
                        },
                        "relation": "related",
                        "dst": {
                            "id": "<THREAT_0x5e7b1981>",
                            "type": "Threat",
                            "value": "shodi"
                        }
                    },
                    {
                        "src": {
                            "id": "<FILE_0xc5e6ecec>",
                            "type": "File",
                            "value": "notepad.exe"
                        },
                        "relation": "use_threat",
                        "dst": {
                            "id": "<THREAT_0x5e7b1981>",
                            "type": "Threat",
                            "value": "shodi"
                        }
                    },
                    {
                        "src": {
                            "id": "<FILE_0x2b48d23a>",
                            "type": "File",
                            "value": "winmine.exe"
                        },
                        "relation": "use_threat",
                        "dst": {
                            "id": "<THREAT_0x5e7b1981>",
                            "type": "Threat",
                            "value": "shodi"
                        }
                    }
                ]
            }
        ]
    },
    "ttps": {
        "TTP": [
            {
                "token": {
                    "id": "<TTP_0x4f6a185>",
                    "type": "TTP",
                    "value": "ta0040"
                },
                "references": {
                    "sentences": [
                        "Impact"
                    ],
                    "titles": [
                        "Rewterz Threat Alert Shodi Malware Active IOCs",
                        "Impact"
                    ]
                },
                "links": [
                    {
                        "src": {
                            "id": "<TTP_0x4f6a185>",
                            "type": "TTP",
                            "value": "ta0040"
                        },
                        "relation": "related",
                        "dst": {
                            "id": "<THREAT_0x5e7b1981>",
                            "type": "Threat",
                            "value": "shodi"
                        }
                    },
                    {
                        "src": {
                            "id": "<TTP_0x4f6a185>",
                            "type": "TTP",
                            "value": "ta0040"
                        },
                        "relation": "has_category",
                        "dst": {
                            "id": "<CATEGORY_0xf1a480bb>",
                            "type": "Category",
                            "value": "malware"
                        }
                    },
                    {
                        "src": {
                            "id": "<TTP_0x4f6a185>",
                            "type": "TTP",
                            "value": "ta0040"
                        },
                        "relation": "use_threat",
                        "dst": {
                            "id": "<THREAT_0x5e7b1981>",
                            "type": "Threat",
                            "value": "shodi"
                        }
                    }
                ]
            }
        ]
    },
    "meanings": {
        "Category": [
            {
                "token": {
                    "id": "<CATEGORY_0xf1a480bb>",
                    "type": "Category",
                    "value": "malware"
                },
                "references": {
                    "sentences": [],
                    "titles": [
                        "Rewterz Threat Alert Shodi Malware Active IOCs"
                    ]
                },
                "links": [
                    {
                        "src": {
                            "id": "<TTP_0x4f6a185>",
                            "type": "TTP",
                            "value": "ta0040"
                        },
                        "relation": "has_category",
                        "dst": {
                            "id": "<CATEGORY_0xf1a480bb>",
                            "type": "Category",
                            "value": "malware"
                        }
                    },
                    {
                        "src": {
                            "id": "<CATEGORY_0xf1a480bb>",
                            "type": "Category",
                            "value": "malware"
                        },
                        "relation": "has_category",
                        "dst": {
                            "id": "<THREAT_0x5e7b1981>",
                            "type": "Threat",
                            "value": "shodi"
                        }
                    }
                ]
            },
            {
                "token": {
                    "id": "<CATEGORY_0x151cee5c>",
                    "type": "Category",
                    "value": "trojan"
                },
                "references": {
                    "sentences": [
                        "W32/Shodi-F a virus targeting Windows platform seeks to infect all files with the EXE extension, except for specific Windows system files. W32/Shodi-F specifically targets Scandskw.exe, Winmine.exe, Sol.exe, Pbrush.exe, and Notepad.exe files in the Windows folder. After targeting, it creates a thread to look for additional exe files on the system, including any open network shares to the infected host. W32/Shodi-F drops Troj/Remadm-C, a remote administration Trojan, and also drops JPG file to the Windows system folder with the USR_Shohdi_Photo_USR.jpg filename."
                    ],
                    "titles": [
                        "Analysis Summary"
                    ]
                },
                "links": [
                    {
                        "src": {
                            "id": "<FILE_0x898f782e>",
                            "type": "File",
                            "value": "usr_shohdi_photo_usr.jpg"
                        },
                        "relation": "has_category",
                        "dst": {
                            "id": "<CATEGORY_0x151cee5c>",
                            "type": "Category",
                            "value": "trojan"
                        }
                    },
                    {
                        "src": {
                            "id": "<CATEGORY_0x151cee5c>",
                            "type": "Category",
                            "value": "trojan"
                        },
                        "relation": "has_category",
                        "dst": {
                            "id": "<THREAT_0x5e7b1981>",
                            "type": "Threat",
                            "value": "shodi"
                        }
                    }
                ]
            }
        ]
    },
    "iocs": {
        "File": [
            {
                "token": {
                    "id": "<FILE_0x68bc808>",
                    "type": "File",
                    "value": "scandskw.exe"
                },
                "references": {
                    "sentences": [
                        "W32/Shodi-F a virus targeting Windows platform seeks to infect all files with the EXE extension, except for specific Windows system files. W32/Shodi-F specifically targets Scandskw.exe, Winmine.exe, Sol.exe, Pbrush.exe, and Notepad.exe files in the Windows folder. After targeting, it creates a thread to look for additional exe files on the system, including any open network shares to the infected host. W32/Shodi-F drops Troj/Remadm-C, a remote administration Trojan, and also drops JPG file to the Windows system folder with the USR_Shohdi_Photo_USR.jpg filename."
                    ],
                    "titles": [
                        "Analysis Summary"
                    ]
                },
                "links": [
                    {
                        "src": {
                            "id": "<FILE_0x68bc808>",
                            "type": "File",
                            "value": "scandskw.exe"
                        },
                        "relation": "related",
                        "dst": {
                            "id": "<UNKNOWNWORD_0xf1dee3d3>",
                            "type": "UnknownWord",
                            "value": "w32"
                        }
                    },
                    {
                        "src": {
                            "id": "<FILE_0x68bc808>",
                            "type": "File",
                            "value": "scandskw.exe"
                        },
                        "relation": "use_threat",
                        "dst": {
                            "id": "<THREAT_0x5e7b1981>",
                            "type": "Threat",
                            "value": "shodi"
                        }
                    },
                    {
                        "src": {
                            "id": "<FILE_0x68bc808>",
                            "type": "File",
                            "value": "scandskw.exe"
                        },
                        "relation": "related",
                        "dst": {
                            "id": "<UNKNOWNWORD_0xd5608609>",
                            "type": "UnknownWord",
                            "value": "shodi-f"
                        }
                    }
                ]
            },
            {
                "token": {
                    "id": "<FILE_0x2b48d23a>",
                    "type": "File",
                    "value": "winmine.exe"
                },
                "references": {
                    "sentences": [
                        "W32/Shodi-F a virus targeting Windows platform seeks to infect all files with the EXE extension, except for specific Windows system files. W32/Shodi-F specifically targets Scandskw.exe, Winmine.exe, Sol.exe, Pbrush.exe, and Notepad.exe files in the Windows folder. After targeting, it creates a thread to look for additional exe files on the system, including any open network shares to the infected host. W32/Shodi-F drops Troj/Remadm-C, a remote administration Trojan, and also drops JPG file to the Windows system folder with the USR_Shohdi_Photo_USR.jpg filename."
                    ],
                    "titles": [
                        "Analysis Summary"
                    ]
                },
                "links": [
                    {
                        "src": {
                            "id": "<FILE_0x2b48d23a>",
                            "type": "File",
                            "value": "winmine.exe"
                        },
                        "relation": "related",
                        "dst": {
                            "id": "<UNKNOWNWORD_0xf1dee3d3>",
                            "type": "UnknownWord",
                            "value": "w32"
                        }
                    },
                    {
                        "src": {
                            "id": "<FILE_0x2b48d23a>",
                            "type": "File",
                            "value": "winmine.exe"
                        },
                        "relation": "use_threat",
                        "dst": {
                            "id": "<THREAT_0x5e7b1981>",
                            "type": "Threat",
                            "value": "shodi"
                        }
                    },
                    {
                        "src": {
                            "id": "<FILE_0x2b48d23a>",
                            "type": "File",
                            "value": "winmine.exe"
                        },
                        "relation": "related",
                        "dst": {
                            "id": "<UNKNOWNWORD_0xd5608609>",
                            "type": "UnknownWord",
                            "value": "shodi-f"
                        }
                    }
                ]
            },
            {
                "token": {
                    "id": "<FILE_0xf4112668>",
                    "type": "File",
                    "value": "sol.exe"
                },
                "references": {
                    "sentences": [
                        "W32/Shodi-F a virus targeting Windows platform seeks to infect all files with the EXE extension, except for specific Windows system files. W32/Shodi-F specifically targets Scandskw.exe, Winmine.exe, Sol.exe, Pbrush.exe, and Notepad.exe files in the Windows folder. After targeting, it creates a thread to look for additional exe files on the system, including any open network shares to the infected host. W32/Shodi-F drops Troj/Remadm-C, a remote administration Trojan, and also drops JPG file to the Windows system folder with the USR_Shohdi_Photo_USR.jpg filename."
                    ],
                    "titles": [
                        "Analysis Summary"
                    ]
                },
                "links": [
                    {
                        "src": {
                            "id": "<FILE_0xf4112668>",
                            "type": "File",
                            "value": "sol.exe"
                        },
                        "relation": "related",
                        "dst": {
                            "id": "<UNKNOWNWORD_0xd5608609>",
                            "type": "UnknownWord",
                            "value": "shodi-f"
                        }
                    },
                    {
                        "src": {
                            "id": "<FILE_0xf4112668>",
                            "type": "File",
                            "value": "sol.exe"
                        },
                        "relation": "related",
                        "dst": {
                            "id": "<UNKNOWNWORD_0xf1dee3d3>",
                            "type": "UnknownWord",
                            "value": "w32"
                        }
                    },
                    {
                        "src": {
                            "id": "<FILE_0xf4112668>",
                            "type": "File",
                            "value": "sol.exe"
                        },
                        "relation": "use_threat",
                        "dst": {
                            "id": "<THREAT_0x5e7b1981>",
                            "type": "Threat",
                            "value": "shodi"
                        }
                    }
                ]
            },
            {
                "token": {
                    "id": "<FILE_0xa612fb14>",
                    "type": "File",
                    "value": "pbrush.exe"
                },
                "references": {
                    "sentences": [
                        "W32/Shodi-F a virus targeting Windows platform seeks to infect all files with the EXE extension, except for specific Windows system files. W32/Shodi-F specifically targets Scandskw.exe, Winmine.exe, Sol.exe, Pbrush.exe, and Notepad.exe files in the Windows folder. After targeting, it creates a thread to look for additional exe files on the system, including any open network shares to the infected host. W32/Shodi-F drops Troj/Remadm-C, a remote administration Trojan, and also drops JPG file to the Windows system folder with the USR_Shohdi_Photo_USR.jpg filename."
                    ],
                    "titles": [
                        "Analysis Summary"
                    ]
                },
                "links": [
                    {
                        "src": {
                            "id": "<FILE_0xa612fb14>",
                            "type": "File",
                            "value": "pbrush.exe"
                        },
                        "relation": "use_threat",
                        "dst": {
                            "id": "<THREAT_0x5e7b1981>",
                            "type": "Threat",
                            "value": "shodi"
                        }
                    },
                    {
                        "src": {
                            "id": "<FILE_0xa612fb14>",
                            "type": "File",
                            "value": "pbrush.exe"
                        },
                        "relation": "related",
                        "dst": {
                            "id": "<UNKNOWNWORD_0xf1dee3d3>",
                            "type": "UnknownWord",
                            "value": "w32"
                        }
                    },
                    {
                        "src": {
                            "id": "<FILE_0xa612fb14>",
                            "type": "File",
                            "value": "pbrush.exe"
                        },
                        "relation": "related",
                        "dst": {
                            "id": "<UNKNOWNWORD_0xd5608609>",
                            "type": "UnknownWord",
                            "value": "shodi-f"
                        }
                    }
                ]
            },
            {
                "token": {
                    "id": "<FILE_0xc5e6ecec>",
                    "type": "File",
                    "value": "notepad.exe"
                },
                "references": {
                    "sentences": [
                        "W32/Shodi-F a virus targeting Windows platform seeks to infect all files with the EXE extension, except for specific Windows system files. W32/Shodi-F specifically targets Scandskw.exe, Winmine.exe, Sol.exe, Pbrush.exe, and Notepad.exe files in the Windows folder. After targeting, it creates a thread to look for additional exe files on the system, including any open network shares to the infected host. W32/Shodi-F drops Troj/Remadm-C, a remote administration Trojan, and also drops JPG file to the Windows system folder with the USR_Shohdi_Photo_USR.jpg filename."
                    ],
                    "titles": [
                        "Analysis Summary"
                    ]
                },
                "links": [
                    {
                        "src": {
                            "id": "<FILE_0xc5e6ecec>",
                            "type": "File",
                            "value": "notepad.exe"
                        },
                        "relation": "related",
                        "dst": {
                            "id": "<UNKNOWNWORD_0xf1dee3d3>",
                            "type": "UnknownWord",
                            "value": "w32"
                        }
                    },
                    {
                        "src": {
                            "id": "<FILE_0xc5e6ecec>",
                            "type": "File",
                            "value": "notepad.exe"
                        },
                        "relation": "use_threat",
                        "dst": {
                            "id": "<THREAT_0x5e7b1981>",
                            "type": "Threat",
                            "value": "shodi"
                        }
                    },
                    {
                        "src": {
                            "id": "<FILE_0xc5e6ecec>",
                            "type": "File",
                            "value": "notepad.exe"
                        },
                        "relation": "related",
                        "dst": {
                            "id": "<UNKNOWNWORD_0xd5608609>",
                            "type": "UnknownWord",
                            "value": "shodi-f"
                        }
                    }
                ]
            },
            {
                "token": {
                    "id": "<FILE_0x898f782e>",
                    "type": "File",
                    "value": "usr_shohdi_photo_usr.jpg"
                },
                "references": {
                    "sentences": [
                        "W32/Shodi-F a virus targeting Windows platform seeks to infect all files with the EXE extension, except for specific Windows system files. W32/Shodi-F specifically targets Scandskw.exe, Winmine.exe, Sol.exe, Pbrush.exe, and Notepad.exe files in the Windows folder. After targeting, it creates a thread to look for additional exe files on the system, including any open network shares to the infected host. W32/Shodi-F drops Troj/Remadm-C, a remote administration Trojan, and also drops JPG file to the Windows system folder with the USR_Shohdi_Photo_USR.jpg filename."
                    ],
                    "titles": [
                        "Analysis Summary"
                    ]
                },
                "links": [
                    {
                        "src": {
                            "id": "<FILE_0x898f782e>",
                            "type": "File",
                            "value": "usr_shohdi_photo_usr.jpg"
                        },
                        "relation": "related",
                        "dst": {
                            "id": "<UNKNOWNWORD_0x612ee271>",
                            "type": "UnknownWord",
                            "value": "troj"
                        }
                    },
                    {
                        "src": {
                            "id": "<FILE_0x898f782e>",
                            "type": "File",
                            "value": "usr_shohdi_photo_usr.jpg"
                        },
                        "relation": "related",
                        "dst": {
                            "id": "<UNKNOWNWORD_0xd5608609>",
                            "type": "UnknownWord",
                            "value": "shodi-f"
                        }
                    },
                    {
                        "src": {
                            "id": "<FILE_0x898f782e>",
                            "type": "File",
                            "value": "usr_shohdi_photo_usr.jpg"
                        },
                        "relation": "related",
                        "dst": {
                            "id": "<UNKNOWNWORD_0xf1dee3d3>",
                            "type": "UnknownWord",
                            "value": "w32"
                        }
                    },
                    {
                        "src": {
                            "id": "<FILE_0x898f782e>",
                            "type": "File",
                            "value": "usr_shohdi_photo_usr.jpg"
                        },
                        "relation": "has_category",
                        "dst": {
                            "id": "<CATEGORY_0x151cee5c>",
                            "type": "Category",
                            "value": "trojan"
                        }
                    },
                    {
                        "src": {
                            "id": "<FILE_0x898f782e>",
                            "type": "File",
                            "value": "usr_shohdi_photo_usr.jpg"
                        },
                        "relation": "use_threat",
                        "dst": {
                            "id": "<THREAT_0x5e7b1981>",
                            "type": "Threat",
                            "value": "shodi"
                        }
                    },
                    {
                        "src": {
                            "id": "<FILE_0x898f782e>",
                            "type": "File",
                            "value": "usr_shohdi_photo_usr.jpg"
                        },
                        "relation": "related",
                        "dst": {
                            "id": "<UNKNOWNWORD_0x74b61997>",
                            "type": "UnknownWord",
                            "value": "remadm-c"
                        }
                    }
                ]
            }
        ],
        "Hash": [
            {
                "token": {
                    "id": "<MD5_0x3a90d8b4>",
                    "type": "Hash",
                    "hash_type": "MD5",
                    "value": "ae2901bab810c3d65352ec82b00e8605"
                },
                "references": {
                    "sentences": [
                        "ae2901bab810c3d65352ec82b00e8605"
                    ],
                    "titles": [
                        "MD5"
                    ]
                },
                "links": [
                    {
                        "src": {
                            "id": "<MD5_0x3a90d8b4>",
                            "type": "Hash",
                            "hash_type": "MD5",
                            "value": "ae2901bab810c3d65352ec82b00e8605"
                        },
                        "relation": "use_threat",
                        "dst": {
                            "id": "<THREAT_0x5e7b1981>",
                            "type": "Threat",
                            "value": "shodi"
                        }
                    }
                ]
            },
            {
                "token": {
                    "id": "<SHA256_0xf2a3ee3c>",
                    "type": "Hash",
                    "hash_type": "SHA256",
                    "value": "849b799a93fc53889229c731b298c9eea699f93790e0387589a155852fb53213"
                },
                "references": {
                    "sentences": [
                        "849b799a93fc53889229c731b298c9eea699f93790e0387589a155852fb53213"
                    ],
                    "titles": [
                        "SHA-256"
                    ]
                },
                "links": [
                    {
                        "src": {
                            "id": "<SHA256_0xf2a3ee3c>",
                            "type": "Hash",
                            "hash_type": "SHA256",
                            "value": "849b799a93fc53889229c731b298c9eea699f93790e0387589a155852fb53213"
                        },
                        "relation": "use_threat",
                        "dst": {
                            "id": "<THREAT_0x5e7b1981>",
                            "type": "Threat",
                            "value": "shodi"
                        }
                    }
                ]
            },
            {
                "token": {
                    "id": "<SHA1_0x41f3cf0a>",
                    "type": "Hash",
                    "hash_type": "SHA1",
                    "value": "af8ddb111e5936a655c44b45b2ee171be4a56d93"
                },
                "references": {
                    "sentences": [
                        "af8ddb111e5936a655c44b45b2ee171be4a56d93"
                    ],
                    "titles": [
                        "SHA-1"
                    ]
                },
                "links": [
                    {
                        "src": {
                            "id": "<SHA1_0x41f3cf0a>",
                            "type": "Hash",
                            "hash_type": "SHA1",
                            "value": "af8ddb111e5936a655c44b45b2ee171be4a56d93"
                        },
                        "relation": "use_threat",
                        "dst": {
                            "id": "<THREAT_0x5e7b1981>",
                            "type": "Threat",
                            "value": "shodi"
                        }
                    }
                ]
            }
        ]
    },
    "unknownwords": {
        "UnknownWord": [
            {
                "token": {
                    "id": "<UNKNOWNWORD_0xf1dee3d3>",
                    "type": "UnknownWord",
                    "value": "w32"
                },
                "references": {
                    "sentences": [
                        "W32/Shodi-F a virus targeting Windows platform seeks to infect all files with the EXE extension, except for specific Windows system files. W32/Shodi-F specifically targets Scandskw.exe, Winmine.exe, Sol.exe, Pbrush.exe, and Notepad.exe files in the Windows folder. After targeting, it creates a thread to look for additional exe files on the system, including any open network shares to the infected host. W32/Shodi-F drops Troj/Remadm-C, a remote administration Trojan, and also drops JPG file to the Windows system folder with the USR_Shohdi_Photo_USR.jpg filename."
                    ],
                    "titles": []
                },
                "links": [
                    {
                        "src": {
                            "id": "<FILE_0xf4112668>",
                            "type": "File",
                            "value": "sol.exe"
                        },
                        "relation": "related",
                        "dst": {
                            "id": "<UNKNOWNWORD_0xf1dee3d3>",
                            "type": "UnknownWord",
                            "value": "w32"
                        }
                    },
                    {
                        "src": {
                            "id": "<FILE_0xc5e6ecec>",
                            "type": "File",
                            "value": "notepad.exe"
                        },
                        "relation": "related",
                        "dst": {
                            "id": "<UNKNOWNWORD_0xf1dee3d3>",
                            "type": "UnknownWord",
                            "value": "w32"
                        }
                    },
                    {
                        "src": {
                            "id": "<FILE_0x68bc808>",
                            "type": "File",
                            "value": "scandskw.exe"
                        },
                        "relation": "related",
                        "dst": {
                            "id": "<UNKNOWNWORD_0xf1dee3d3>",
                            "type": "UnknownWord",
                            "value": "w32"
                        }
                    },
                    {
                        "src": {
                            "id": "<FILE_0x898f782e>",
                            "type": "File",
                            "value": "usr_shohdi_photo_usr.jpg"
                        },
                        "relation": "related",
                        "dst": {
                            "id": "<UNKNOWNWORD_0xf1dee3d3>",
                            "type": "UnknownWord",
                            "value": "w32"
                        }
                    },
                    {
                        "src": {
                            "id": "<FILE_0xa612fb14>",
                            "type": "File",
                            "value": "pbrush.exe"
                        },
                        "relation": "related",
                        "dst": {
                            "id": "<UNKNOWNWORD_0xf1dee3d3>",
                            "type": "UnknownWord",
                            "value": "w32"
                        }
                    },
                    {
                        "src": {
                            "id": "<FILE_0x2b48d23a>",
                            "type": "File",
                            "value": "winmine.exe"
                        },
                        "relation": "related",
                        "dst": {
                            "id": "<UNKNOWNWORD_0xf1dee3d3>",
                            "type": "UnknownWord",
                            "value": "w32"
                        }
                    }
                ]
            },
            {
                "token": {
                    "id": "<UNKNOWNWORD_0xd5608609>",
                    "type": "UnknownWord",
                    "value": "shodi-f"
                },
                "references": {
                    "sentences": [
                        "W32/Shodi-F a virus targeting Windows platform seeks to infect all files with the EXE extension, except for specific Windows system files. W32/Shodi-F specifically targets Scandskw.exe, Winmine.exe, Sol.exe, Pbrush.exe, and Notepad.exe files in the Windows folder. After targeting, it creates a thread to look for additional exe files on the system, including any open network shares to the infected host. W32/Shodi-F drops Troj/Remadm-C, a remote administration Trojan, and also drops JPG file to the Windows system folder with the USR_Shohdi_Photo_USR.jpg filename."
                    ],
                    "titles": []
                },
                "links": [
                    {
                        "src": {
                            "id": "<FILE_0xa612fb14>",
                            "type": "File",
                            "value": "pbrush.exe"
                        },
                        "relation": "related",
                        "dst": {
                            "id": "<UNKNOWNWORD_0xd5608609>",
                            "type": "UnknownWord",
                            "value": "shodi-f"
                        }
                    },
                    {
                        "src": {
                            "id": "<FILE_0xc5e6ecec>",
                            "type": "File",
                            "value": "notepad.exe"
                        },
                        "relation": "related",
                        "dst": {
                            "id": "<UNKNOWNWORD_0xd5608609>",
                            "type": "UnknownWord",
                            "value": "shodi-f"
                        }
                    },
                    {
                        "src": {
                            "id": "<FILE_0x898f782e>",
                            "type": "File",
                            "value": "usr_shohdi_photo_usr.jpg"
                        },
                        "relation": "related",
                        "dst": {
                            "id": "<UNKNOWNWORD_0xd5608609>",
                            "type": "UnknownWord",
                            "value": "shodi-f"
                        }
                    },
                    {
                        "src": {
                            "id": "<FILE_0x2b48d23a>",
                            "type": "File",
                            "value": "winmine.exe"
                        },
                        "relation": "related",
                        "dst": {
                            "id": "<UNKNOWNWORD_0xd5608609>",
                            "type": "UnknownWord",
                            "value": "shodi-f"
                        }
                    },
                    {
                        "src": {
                            "id": "<FILE_0xf4112668>",
                            "type": "File",
                            "value": "sol.exe"
                        },
                        "relation": "related",
                        "dst": {
                            "id": "<UNKNOWNWORD_0xd5608609>",
                            "type": "UnknownWord",
                            "value": "shodi-f"
                        }
                    },
                    {
                        "src": {
                            "id": "<FILE_0x68bc808>",
                            "type": "File",
                            "value": "scandskw.exe"
                        },
                        "relation": "related",
                        "dst": {
                            "id": "<UNKNOWNWORD_0xd5608609>",
                            "type": "UnknownWord",
                            "value": "shodi-f"
                        }
                    }
                ]
            },
            {
                "token": {
                    "id": "<UNKNOWNWORD_0x612ee271>",
                    "type": "UnknownWord",
                    "value": "troj"
                },
                "references": {
                    "sentences": [
                        "W32/Shodi-F a virus targeting Windows platform seeks to infect all files with the EXE extension, except for specific Windows system files. W32/Shodi-F specifically targets Scandskw.exe, Winmine.exe, Sol.exe, Pbrush.exe, and Notepad.exe files in the Windows folder. After targeting, it creates a thread to look for additional exe files on the system, including any open network shares to the infected host. W32/Shodi-F drops Troj/Remadm-C, a remote administration Trojan, and also drops JPG file to the Windows system folder with the USR_Shohdi_Photo_USR.jpg filename."
                    ],
                    "titles": []
                },
                "links": [
                    {
                        "src": {
                            "id": "<FILE_0x898f782e>",
                            "type": "File",
                            "value": "usr_shohdi_photo_usr.jpg"
                        },
                        "relation": "related",
                        "dst": {
                            "id": "<UNKNOWNWORD_0x612ee271>",
                            "type": "UnknownWord",
                            "value": "troj"
                        }
                    }
                ]
            },
            {
                "token": {
                    "id": "<UNKNOWNWORD_0x74b61997>",
                    "type": "UnknownWord",
                    "value": "remadm-c"
                },
                "references": {
                    "sentences": [
                        "W32/Shodi-F a virus targeting Windows platform seeks to infect all files with the EXE extension, except for specific Windows system files. W32/Shodi-F specifically targets Scandskw.exe, Winmine.exe, Sol.exe, Pbrush.exe, and Notepad.exe files in the Windows folder. After targeting, it creates a thread to look for additional exe files on the system, including any open network shares to the infected host. W32/Shodi-F drops Troj/Remadm-C, a remote administration Trojan, and also drops JPG file to the Windows system folder with the USR_Shohdi_Photo_USR.jpg filename."
                    ],
                    "titles": []
                },
                "links": [
                    {
                        "src": {
                            "id": "<FILE_0x898f782e>",
                            "type": "File",
                            "value": "usr_shohdi_photo_usr.jpg"
                        },
                        "relation": "related",
                        "dst": {
                            "id": "<UNKNOWNWORD_0x74b61997>",
                            "type": "UnknownWord",
                            "value": "remadm-c"
                        }
                    }
                ]
            }
        ]
    },
    "other_links": [],
    "info": {
        "potential_threats": {},
        "sigma": false,
        "yara": false
    },
    "keywords": {
        "classified": [],
        "dubbed": [],
        "associated": [],
        "targets": [
            "W32/Shodi-F specifically targets Scandskw.exe, Winmine.exe, Sol.exe, Pbrush.exe, and Notepad.exe files in the Windows folder"
        ],
        "attributed": []
    },
    "resources": {
        "links": {
            "github": [],
            "pastebin": [],
            "text_files": [],
            "other": []
        },
        "images": [
            "https://www.rewterz.com/wp-content/uploads/2020/03/logo_color_small.png"
        ]
    }
}