{"id": "report_0x376377a2", "report_date": "2022-05-11T00:00:00Z", "report_title": "Operation RestyLink:", "report_url": "https://insight-jp.nttsecurity.com/post/102ho8o/operation-restylink", "chapter": ["Operation RestyLink:", "LNK", "DOT", "20224", "20223", "20221", "202111", "202110", "DarkHotel", "Kimsuky", "APT29", "TA416", "IoCs", "References"], "threat": ["cobalt_strike", "darkhotel_group", "kimsuky_group", "duke_group", "red_delta_group", "lazarus_group", "darkhalo_group", "flagpro", "blacktech_group"], "category": ["c2", "fraud", "phishing", "malware", "rat"], "industry": ["government"], "geo": ["dprk", "ukraine", "japan"], "cve": [], "ttp": [], "detect": []}